streamgraph/__init__.py
streamgraph/components.py
streamgraph/conditional_nodes.py
streamgraph/utils.py
streamgraph_python-0.1.2.dist-info/LICENSE
streamgraph_python-0.1.2.dist-info/METADATA
streamgraph_python-0.1.2.dist-info/WHEEL
streamgraph_python-0.1.2.dist-info/RECORD
