Metadata-Version: 2.1
Name: streamgraph-python
Version: 0.1.2
Summary: A library for creating and managing chains of function nodes.
Home-page: https://github.com/lf-data/streamgraph
License: MIT
Author: Francesco Lorè
Author-email: flore9819@gmail.com
Requires-Python: >=3.9
Classifier: License :: OSI Approved :: MIT License
Classifier: Operating System :: OS Independent
Classifier: Programming Language :: Python :: 3
Classifier: Programming Language :: Python :: 3.9
Classifier: Programming Language :: Python :: 3.10
Classifier: Programming Language :: Python :: 3.11
Classifier: Programming Language :: Python :: 3.12
Requires-Dist: colorama (>=0.4.6,<0.5.0)
Requires-Dist: python-json-logger (>=2.0.7,<3.0.0)
Requires-Dist: requests (>=2.32.3,<3.0.0)
Project-URL: Bug Tracker, https://github.com/lf-data/streamgraph/issues
Project-URL: Repository, https://github.com/lf-data/streamgraph
